[
    {
        "id": 1,
        "name": "January",
        "acceptedRequests": 56,
        "loanReturnTime": 7,
        "budget": 3000
    },
    {
        "id": 2,
        "name": "February",
        "acceptedRequests": 45,
        "loanReturnTime": 12,
        "budget": 5000
    },
    {
        "id": 3,
        "name": "March",
        "acceptedRequests": 55,
        "loanReturnTime": 7,
        "budget": 2000
    },
    {
        "id": 4,
        "name": "April",
        "acceptedRequests": 35,
        "loanReturnTime": 5,
        "budget": 1000
    },
    {
        "id": 5,
        "name": "May",
        "acceptedRequests": 45,
        "loanReturnTime": 9,
        "budget": 8000
    },
    {
        "id": 6,
        "name": "June",
        "acceptedRequests": 35,
        "loanReturnTime": 12,
        "budget": 5000
    },
    {
        "id": 7,
        "name": "July",
        "acceptedRequests": 43,
        "loanReturnTime": 11,
        "budget": 6000
    },
    {
        "id": 8,
        "name": "August",
        "acceptedRequests": 33,
        "loanReturnTime": 19,
        "budget": 3000
    },
    {
        "id": 9,
        "name": "September",
        "acceptedRequests": 63,
        "loanReturnTime": 28,
        "budget": 4000
    },
    {
        "id": 10,
        "name": "October",
        "acceptedRequests": 53,
        "loanReturnTime": 29,
        "budget": 8000
    },
    {
        "id": 11,
        "name": "November",
        "acceptedRequests": 51,
        "loanReturnTime": 80,
        "budget": 7000
    },
    {
        "id": 12,
        "name": "December",
        "acceptedRequests": 59,
        "loanReturnTime": 72,
        "budget": 3000
    }
]